vidmux/__init__.py
vidmux/__main__.py
vidmux/cli.py
vidmux/filesystem.py
vidmux/language_tools.py
vidmux/languages.py
vidmux/mux_audio_tracks.py
vidmux/renaming.py
vidmux/srt_tools.py
vidmux/video_inspection.py
vidmux/video_library_scan.py
vidmux/_legacy/__init__.py
vidmux/_legacy/filename_heuristics.py
vidmux/_legacy/library_structure_rules.py
vidmux/library_structure/__init__.py
vidmux/library_structure/core.py
vidmux/library_structure/rules.py
vidmux/library_structure/structure_scan.py
vidmux/media/__init__.py
vidmux/media/models.py
vidmux/media/naming.py
vidmux/media/parsing.py
vidmux/media/version_tags.py
vidmux-0.2.1.dist-info/licenses/LICENSE
vidmux-0.2.1.dist-info/METADATA
vidmux-0.2.1.dist-info/WHEEL
vidmux-0.2.1.dist-info/entry_points.txt
vidmux-0.2.1.dist-info/top_level.txt
vidmux-0.2.1.dist-info/RECORD
