Metadata-Version: 2.4
Name: vidmux
Version: 0.2.1
Summary: Inspect and modify video/audio/subtitle tracks using FFmpeg.
Author-email: Philipp Meder <148459685+PhilippMeder@users.noreply.github.com>
Maintainer-email: Philipp Meder <148459685+PhilippMeder@users.noreply.github.com>
License: BSD 3-Clause License
Project-URL: Changelog, https://github.com/PhilippMeder/vidmux/commits
Project-URL: Documentation, https://github.com/PhilippMeder/vidmux/README.md
Project-URL: Download, https://github.com/PhilippMeder/vidmux
Project-URL: Homepage, https://github.com/PhilippMeder/vidmux
Project-URL: Issues, https://github.com/PhilippMeder/vidmux/issues
Project-URL: Releasenotes, https://github.com/PhilippMeder/vidmux/commits
Project-URL: Source, https://github.com/PhilippMeder/vidmux.git
Keywords: media,video,inspect,mux,audio tracks,cli,subtitles,movie library
Classifier: Intended Audience :: End Users/Desktop
Classifier: License :: OSI Approved :: BSD License
Classifier: Operating System :: OS Independent
Classifier: Programming Language :: Python :: 3
Classifier: Programming Language :: Python :: 3.10
Classifier: Programming Language :: Python :: 3.11
Classifier: Programming Language :: Python :: 3.12
Classifier: Programming Language :: Python :: 3.13
Classifier: Programming Language :: Python :: 3.14
Classifier: Topic :: Multimedia
Classifier: Topic :: Multimedia :: Video
Classifier: Topic :: Utilities
Requires-Python: >=3.10
License-File: LICENSE
Provides-Extra: dev
Requires-Dist: pytest; extra == "dev"
Requires-Dist: ruff; extra == "dev"
Dynamic: license-file
